ch06/__init__.py
ch06/mcp_client.py
ch06/weather.py
ch07/__init__.py
ch07/weather.py
mcp_lite_dev-0.1.2.dist-info/METADATA
mcp_lite_dev-0.1.2.dist-info/WHEEL
mcp_lite_dev-0.1.2.dist-info/entry_points.txt
mcp_lite_dev-0.1.2.dist-info/top_level.txt
mcp_lite_dev-0.1.2.dist-info/RECORD
