Metadata-Version: 2.4
Name: mcp-lite-dev
Version: 0.1.2
Summary: 《MCP极简开发》项目代码
Requires-Python: >=3.10
Requires-Dist: httpx>=0.28.1
Requires-Dist: mcp>=1.10.1
Requires-Dist: openai>=1.93.3
Requires-Dist: pip>=25.1.1
Requires-Dist: python-dotenv>=1.1.1
Requires-Dist: setuptools>=80.9.0
Requires-Dist: wheel>=0.45.1
